{
  "identify": "PCD-91-家訴-31-20020418-1",
  "court": {
    "name": "臺灣新北地方法院",
    "code": "PCD"
  },
  "division": {
    "name": "民事",
    "code": "V"
  },
  "year": 91,
  "word": "家訴",
  "number": "31",
  "jcheck": "1",
  "reason": "確認遺囑有效",
  "content": "臺灣板橋地方法院民事裁定  九十一年度家訴字第三一號\n    聲  請  人  甲○○\n右原告請求確認遺囑有效事件，本院裁定如左：\n    主      文\n原告應於本裁定送達後伍日內，補正起訴狀上被告之姓名、真正住所或居所，逾期即\n駁回其訴。\n    理      由\n一、按當事人書狀，應記載當事人姓名、性別、年齡、職業及住所或居所，當事人為\n    法人或其他團體者，應記載其名稱及事務所或營業所，民事訴訟法第一百十六條\n    第一項定有明文。\n二、本件原告起訴，未據於起訴狀上載明被告之姓名及真正住所或居所，致起訴不合\n    程式，於法不合，應定期間命其補正。\n三、依民事訴訟法第一百二十一條第一項，裁定如主文。\n中      華      民      國    九十一    年      四      月     十八     日\n                                    臺灣板橋地方法院民事第家事庭\n~B法      官  陳明珠\n右正本證明與原本無異\n中      華      民      國    九十一    年      四      月     十八     日\n~B法院書記官  劉日賓\n",
  "structure": {
    "main": "原告應於本裁定送達後伍日內，補正起訴狀上被告之姓名、真正住所或居所，逾期即\n駁回其訴。",
    "reason": "一、按當事人書狀，應記載當事人姓名、性別、年齡、職業及住所或居所，當事人為\n    法人或其他團體者，應記載其名稱及事務所或營業所，民事訴訟法第一百十六條\n    第一項定有明文。\n二、本件原告起訴，未據於起訴狀上載明被告之姓名及真正住所或居所，致起訴不合\n    程式，於法不合，應定期間命其補正。\n三、依民事訴訟法第一百二十一條第一項，裁定如主文。"
  },
  "search": "臺灣板橋地方法院民事裁定九十一年度家訴字第三一號聲請人甲○○右原告請求確認遺囑有效事件，本院裁定如左：主文原告應於本裁定送達後伍日內，補正起訴狀上被告之姓名、真正住所或居所，逾期即駁回其訴。理由一、按當事人書狀，應記載當事人姓名、性別、年齡、職業及住所或居所，當事人為法人或其他團體者，應記載其名稱及事務所或營業所，民事訴訟法第一百十六條第一項定有明文。二、本件原告起訴，未據於起訴狀上載明被告之姓名及真正住所或居所，致起訴不合程式，於法不合，應定期間命其補正。三、依民事訴訟法第一百二十一條第一項，裁定如主文。中華民國九十一年四月十八日臺灣板橋地方法院民事第家事庭~B法官陳明珠右正本證明與原本無異中華民國九十一年四月十八日~B法院書記官劉日賓",
  "characters": {
    "judges": [
      "陳明珠"
    ],
    "prosecutors": [

    ],
    "lawyers": [

    ],
    "clerks": [

    ],
    "plaintiffs": [

    ],
    "defendants": [

    ],
    "prosecutor_office": [
      "甲"
    ],
    "creditors": [

    ],
    "debtors": [

    ],
    "judicial_associate_officer": [

    ]
  },
  "adjudged_at": "2002-04-18",
  "created_at": "2016-02-04 15:37:10",
  "updated_at": "2016-02-04 15:37:10"
}